full_adder.v
module full_adder(s,c,x,y,z);
	input x,y,z;
	output s,c;

	assign s = x^(y^z);
	assign c = x&y | y&z | x&z;
endmodule

module testbench;
	reg x,y,z;
	wire s,c;
	full_adder f(s,c,x,y,z);

	initial
	begin
		$dumpfile ("full_adder.vcd");
		$dumpvars (0,testbench);
		$monitor ($time,"X = %b   Y = %b  Z = %b  Sum = %b  Carry = %b",x,y,z,s,c);
		#5 x=0;y=0;z=0;
		#5 x=0;y=0;z=1;
		#5 x=0;y=1;z=0;
		#5 x=0;y=1;z=1;
		#5 x=1;y=0;z=0;
		#5 x=1;y=0;z=1;
		#5 x=1;y=1;z=0;
		#5 x=1;y=1;z=1;
		#5 $finish;
	end
endmodule

full_adder.vcd
$date
	Fri Oct 19 01:02:07 2018
$end
$version
	Icarus Verilog
$end
$timescale
	1s
$end
$scope module testbench $end
$var wire 1 ! s $end
$var wire 1 " c $end
$var reg 1 # x $end
$var reg 1 $ y $end
$var reg 1 % z $end
$scope module f $end
$var wire 1 " c $end
$var wire 1 ! s $end
$var wire 1 # x $end
$var wire 1 $ y $end
$var wire 1 % z $end
$upscope $end
$upscope $end
$enddefinitions $end
#0
$dumpvars
x%
x$
x#
x"
x!
$end
#5
0"
0!
0%
0$
0#
#10
1!
1%
#15
0%
1$
#20
1"
0!
1%
#25
0"
1!
0%
0$
1#
#30
0!
1"
1%
#35
0%
1$
#40
1!
1%
